LICENSE
MANIFEST.in
README.org
setup.py
Gitissius.egg-info/PKG-INFO
Gitissius.egg-info/SOURCES.txt
Gitissius.egg-info/dependency_links.txt
Gitissius.egg-info/entry_points.txt
Gitissius.egg-info/top_level.txt
gitissius/__init__.py
gitissius/common.py
gitissius/database.py
gitissius/gitissius.py
gitissius/gitshelve.py
gitissius/properties.py
gitissius/commands/__init__.py
gitissius/commands/close.py
gitissius/commands/comment_issue.py
gitissius/commands/delete_issue.py
gitissius/commands/edit_issue.py
gitissius/commands/list_issues.py
gitissius/commands/list_my_issues.py
gitissius/commands/new_issue.py
gitissius/commands/pull.py
gitissius/commands/push.py
gitissius/commands/show_issue.py
gitissius/commands/update.py