Metadata-Version: 1.0
Name: Gitissius
Version: 0.1.6
Summary: Distributed bug tracking for Git.
Home-page: http://github.com/glogiotatidis/gitissius
Author: Giorgos Logiotatidis
Author-email: seadog@sealabs.net
License: Mixed
Keywords: bug,tracking,git,distributed
Platform: UNKNOWN
Classifier: Topic :: Software Development :: Bug Tracking
Classifier: Development Status :: 4 - Beta
Classifier: License :: Freely Distributable
Classifier: License :: OSI Approved :: GNU General Public License (GPL)
